{
  "id": "quiz2",
  "name": "General Knowledge Quiz",
  "author": "Todor",
  "time_limit": 10,
  "questions": [
    {
      "question": "What is the capital of France?",
      "options": ["London", "Berlin", "Paris", "Madrid"],
      "answer": "Paris"
    },
    {
      "question": "What is 5 multiplied by 6?",
      "options": ["11", "30", "35", "60"],
      "answer": "30"
    },
    {
      "question": "Which planet is known as the Red Planet?",
      "options": ["Earth", "Mars", "Jupiter", "Saturn"],
      "answer": "Mars"
    },
    {
      "question": "What language is primarily used for Android development?",
      "options": ["Swift", "Kotlin", "Python", "Ruby"],
      "answer": "Kotlin"
    },
    {
      "question": "Look at the image and name the landmark shown.",
      "options": [],
      "answer": "Eiffel Tower",
      "image": "C:\\Users\\totin\\OneDrive\\Работен плот\\Project\\Images\\eiffeltower.jpg"
    }
  ]
}
